Metadata-Version: 2.1
Name: odoo10-addon-l10n-br-resource
Version: 10.0.1.0.0.99.dev34
Summary: This module extend core resource to create important brazilian informations. Define a Brazilian calendar and some tools to compute dates used in financial and payroll modules
Home-page: https://github.com/OCA/l10n-brazil
Author: KMEE,Odoo Community Association (OCA)
Author-email: support@odoo-community.org
License: AGPL-3
Platform: UNKNOWN
Classifier: Programming Language :: Python
Classifier: Framework :: Odoo
Classifier: Framework :: Odoo :: 10.0
Classifier: License :: OSI Approved :: GNU Affero General Public License v3
Requires-Python: ~=2.7
Requires-Dist: odoo10-addon-l10n-br-base
Requires-Dist: odoo <10.1dev,>=10.0
Requires-Dist: pybrasil
